README.md
setup.py
pypremiumsim/DataVolume.py
pypremiumsim/PyPremiumSIM.py
pypremiumsim/__init__.py
pypremiumsim.egg-info/PKG-INFO
pypremiumsim.egg-info/SOURCES.txt
pypremiumsim.egg-info/dependency_links.txt
pypremiumsim.egg-info/requires.txt
pypremiumsim.egg-info/top_level.txt