Metadata-Version: 2.1
Name: pypremiumsim
Version: 0.0.2
Summary: PremiumSIM API (Unofficial). Access basic account details and status information.
Home-page: https://github.com/skhg/pyPremiumSIM
Author: Jack Higgins
Author-email: pypi@jackhiggins.ie
License: MIT
Keywords: PremiumSIM mobile phone handy balance status web germany deutschland scraper api
Platform: UNKNOWN
Classifier: Development Status :: 4 - Beta
Classifier: License :: OSI Approved :: MIT License
Classifier: Programming Language :: Python :: 2.7
Classifier: Programming Language :: Python :: 3.6
